{"is_source_file": true, "format": "JavaScript (React component)", "description": "This file defines a React functional component named Sidebar, which displays navigation links and a list of user playlists, allowing for playlist creation via an API call.", "external_files": ["../hooks/usePlaylists", "../api/apiClient", "./Sidebar.css"], "external_methods": ["usePlaylists", "createPlaylist"], "published": ["Sidebar"], "classes": [], "methods": [{"name": "Sidebar()", "description": "React functional component that displays navigation menu and user playlists, includes functionality to create new playlists.", "scope": "", "scopeKind": ""}, {"name": "handleCreatePlaylist", "description": "Handles user interaction for creating a new playlist, prompts for name, calls API, and updates playlist list."}], "calls": ["usePlaylists", "createPlaylist", "refetch", "prompt", "alert", "console.error"], "search-terms": ["Sidebar React component", "usePlaylists hook", "createPlaylist API call", "playlist creation UI", "playlist list display"], "state": 2, "file_id": 17, "knowledge_revision": 102, "git_revision": "15b5fe2f2e08d5b1071e82e9c349f3027c9d465c", "revision_history": [{"47": "27255446491d69ea7711e55a97f7f094574a9b5f"}, {"86": "59e3c82e93a4e472eb0095f4bd47ae2339c618ae"}, {"102": "15b5fe2f2e08d5b1071e82e9c349f3027c9d465c"}], "ctags": [{"_type": "tag", "name": "Sidebar", "path": "/home/kavia/workspace/code-generation/music-streamer-platform-296479-296488/react_frontend/src/components/Sidebar.js", "pattern": "/^function Sidebar() {$/", "language": "JavaScript", "kind": "function", "signature": "()"}, {"_type": "tag", "name": "handleCreatePlaylist", "path": "/home/kavia/workspace/code-generation/music-streamer-platform-296479-296488/react_frontend/src/components/Sidebar.js", "pattern": "/^            onClick={handleCreatePlaylist}$/", "language": "JavaScript", "kind": "field", "scope": "Sidebar.onClick", "scopeKind": "class"}, {"_type": "tag", "name": "isCreating", "path": "/home/kavia/workspace/code-generation/music-streamer-platform-296479-296488/react_frontend/src/components/Sidebar.js", "pattern": "/^            disabled={isCreating}$/", "language": "JavaScript", "kind": "field", "scope": "Sidebar.disabled", "scopeKind": "class"}], "hash": "ae4dae05fddd228a66f287b85640a33e", "format-version": 4, "code-base-name": "react_frontend", "filename": "react_frontend/src/components/Sidebar.js", "fields": [{"name": "onClick={handleCreatePlaylist}", "scope": "Sidebar.onClick", "scopeKind": "class", "description": "unavailable"}, {"name": "disabled={isCreating}", "scope": "Sidebar.disabled", "scopeKind": "class", "description": "unavailable"}]}